MANIFEST.in
README.md
setup.py
statcode/__init__.py
statcode/__main__.py
statcode/code_descriptions.yml
statcode/copyright_description.yml
statcode/header_descriptions.yml
statcode/statcode.py
statcode.egg-info/PKG-INFO
statcode.egg-info/SOURCES.txt
statcode.egg-info/dependency_links.txt
statcode.egg-info/entry_points.txt
statcode.egg-info/requires.txt
statcode.egg-info/top_level.txt