Metadata-Version: 1.2
Name: statcode
Version: 2.0.0
Summary: Like man pages, but for HTTP status codes
Home-page: https://github.com/shobrook/statcode
Author: shobrook
Author-email: shobrookj@gmail.com
License: MIT
Platform: UNKNOWN
Requires-Python: >=3
